AUTHORS
LICENSE
MANIFEST.in
README.txt
setup.py
clise/__init__.py
clise/__main__.py
clise/cmdscript.py
clise/convtool.py
clise/demo.py
clise/fitstool.py
clise/heron.py
clise/jsontool.py
clise/plottool.py
clise/rabbit.py
clise/rebin.py
clise/tabletool.py
clise/xray_mirror.py
clise.egg-info/PKG-INFO
clise.egg-info/SOURCES.txt
clise.egg-info/dependency_links.txt
clise.egg-info/entry_points.txt
clise.egg-info/requires.txt
clise.egg-info/top_level.txt
clise/doc/heron.md
clise/examples/cmd.sh
clise/examples/demo_autogen_by_file.json5
clise/examples/demo_autogen_by_file_native.json5
clise/examples/demo_autogen_by_file_native_bundles.json5
clise/examples/demo_autogen_by_file_native_bundles_file.json5
clise/examples/demo_autogen_by_id.json5
clise/examples/demo_autogen_by_id_native.json5
clise/examples/demo_autogen_by_id_native_bundles.json5
clise/examples/demo_autogen_by_id_native_bundles_file.json5
clise/examples/demo_by_file.json5
clise/examples/demo_by_files.json5
clise/examples/demo_explicit_tasks.json5
clise/examples/demo_one_task.json5
clise/examples/demo_replace_pars.json5
clise/examples/demo_simple_dict.json5
clise/examples/demo_two_by_files_gen.json5
clise/examples/demo_two_by_files_gen_complete.json5
clise/examples/demo_two_by_files_gen_double.json5
clise/examples/demo_two_tasks.json5
clise/examples/demo_two_tasks_complete.json5
clise/examples/test.sh
clise/startup/cmdline_rabbit.json5
clise/startup/scan_hdus_plot1d_rabbit.json5
clise/startup/scan_hdus_plot1d_rabbit_noswap.json5
clise/startup/startup.json5