Metadata-Version: 2.1
Name: clise
Version: 0.2.2
Summary: Command liner with JSON based input file
Home-page: https://pypi.org/project/clise/0.2.2
Author: Jaesub Hong
Author-email: jhong@cfa.harvard.edu
Classifier: Programming Language :: Python :: 3
Classifier: License :: OSI Approved :: MIT License
Classifier: Operating System :: OS Independent
Requires-Python: >=3.8
License-File: LICENSE
License-File: AUTHORS
